{"School":{"Id":280001023,"Name":"Hale Middle School","CountyId":28,"DistrictId":280001,"Lat":41.32059860229492,"Lon":-96.00810241699219},"EnrollmentByYear":[{"Year":"20022003","Teachers":35,"Students":479,"GradeEnrollment":[{"Grade":"07","EnrollmentSize":224},{"Grade":"08","EnrollmentSize":240},{"Grade":"09","EnrollmentSize":6},{"Grade":"10","EnrollmentSize":8},{"Grade":"11","EnrollmentSize":1}]},{"Year":"20032004","Teachers":36,"Students":462,"GradeEnrollment":[{"Grade":"07","EnrollmentSize":218},{"Grade":"08","EnrollmentSize":244}]},{"Year":"20042005","Teachers":36,"Students":411,"GradeEnrollment":[{"Grade":"07","EnrollmentSize":195},{"Grade":"08","EnrollmentSize":216}]},{"Year":"20052006","Teachers":33,"Students":351,"GradeEnrollment":[{"Grade":"07","EnrollmentSize":169},{"Grade":"08","EnrollmentSize":181},{"Grade":"12","EnrollmentSize":1}]},{"Year":"20062007","Teachers":35,"Students":366,"GradeEnrollment":[{"Grade":"07","EnrollmentSize":173},{"Grade":"08","EnrollmentSize":193}]},{"Year":"20072008","Teachers":0,"Students":297,"GradeEnrollment":[{"Grade":"07","EnrollmentSize":131},{"Grade":"08","EnrollmentSize":166}]},{"Year":"20082009","Teachers":0,"Students":290,"GradeEnrollment":[{"Grade":"07","EnrollmentSize":144},{"Grade":"08","EnrollmentSize":146}]},{"Year":"20092010","Teachers":0,"Students":310,"GradeEnrollment":[{"Grade":"07","EnrollmentSize":146},{"Grade":"08","EnrollmentSize":164}]},{"Year":"20102011","Teachers":0,"Students":319,"GradeEnrollment":[{"Grade":"07","EnrollmentSize":157},{"Grade":"08","EnrollmentSize":162}]},{"Year":"20112012","Teachers":0,"Students":370,"GradeEnrollment":[{"Grade":"07","EnrollmentSize":203},{"Grade":"08","EnrollmentSize":167}]},{"Year":"20122013","Teachers":0,"Students":373,"GradeEnrollment":[{"Grade":"07","EnrollmentSize":180},{"Grade":"08","EnrollmentSize":193}]}]}