{"School":{"Id":770001004,"Name":"Bellevue West Sr High School","CountyId":77,"DistrictId":770001,"Lat":41.16960144042969,"Lon":-96.04019927978516},"EnrollmentByYear":[{"Year":"20022003","Teachers":84,"Students":1412,"GradeEnrollment":[{"Grade":"09","EnrollmentSize":379},{"Grade":"10","EnrollmentSize":356},{"Grade":"11","EnrollmentSize":347},{"Grade":"12","EnrollmentSize":330}]},{"Year":"20032004","Teachers":86,"Students":1429,"GradeEnrollment":[{"Grade":"09","EnrollmentSize":368},{"Grade":"10","EnrollmentSize":362},{"Grade":"11","EnrollmentSize":358},{"Grade":"12","EnrollmentSize":341}]},{"Year":"20042005","Teachers":87,"Students":1471,"GradeEnrollment":[{"Grade":"09","EnrollmentSize":394},{"Grade":"10","EnrollmentSize":363},{"Grade":"11","EnrollmentSize":365},{"Grade":"12","EnrollmentSize":349}]},{"Year":"20052006","Teachers":89,"Students":1520,"GradeEnrollment":[{"Grade":"09","EnrollmentSize":419},{"Grade":"10","EnrollmentSize":380},{"Grade":"11","EnrollmentSize":354},{"Grade":"12","EnrollmentSize":367}]},{"Year":"20062007","Teachers":94,"Students":1486,"GradeEnrollment":[{"Grade":"09","EnrollmentSize":384},{"Grade":"10","EnrollmentSize":400},{"Grade":"11","EnrollmentSize":370},{"Grade":"12","EnrollmentSize":332}]},{"Year":"20072008","Teachers":0,"Students":1574,"GradeEnrollment":[{"Grade":"09","EnrollmentSize":431},{"Grade":"10","EnrollmentSize":375},{"Grade":"11","EnrollmentSize":409},{"Grade":"12","EnrollmentSize":359}]},{"Year":"20082009","Teachers":0,"Students":1600,"GradeEnrollment":[{"Grade":"09","EnrollmentSize":439},{"Grade":"10","EnrollmentSize":420},{"Grade":"11","EnrollmentSize":373},{"Grade":"12","EnrollmentSize":368}]},{"Year":"20092010","Teachers":0,"Students":1594,"GradeEnrollment":[{"Grade":"09","EnrollmentSize":403},{"Grade":"10","EnrollmentSize":415},{"Grade":"11","EnrollmentSize":391},{"Grade":"12","EnrollmentSize":385}]},{"Year":"20102011","Teachers":0,"Students":1668,"GradeEnrollment":[{"Grade":"09","EnrollmentSize":425},{"Grade":"10","EnrollmentSize":405},{"Grade":"11","EnrollmentSize":410},{"Grade":"12","EnrollmentSize":428}]},{"Year":"20112012","Teachers":0,"Students":1669,"GradeEnrollment":[{"Grade":"09","EnrollmentSize":416},{"Grade":"10","EnrollmentSize":442},{"Grade":"11","EnrollmentSize":390},{"Grade":"12","EnrollmentSize":421}]},{"Year":"20122013","Teachers":0,"Students":1575,"GradeEnrollment":[{"Grade":"09","EnrollmentSize":343},{"Grade":"10","EnrollmentSize":398},{"Grade":"11","EnrollmentSize":428},{"Grade":"12","EnrollmentSize":406}]}]}