{"School":{"Id":770001007,"Name":"Bertha Barber Elementary Sch","CountyId":77,"DistrictId":770001,"Lat":41.14580154418945,"Lon":-95.8917007446289},"EnrollmentByYear":[{"Year":"20022003","Teachers":12,"Students":180,"GradeEnrollment":[{"Grade":"PK","EnrollmentSize":8},{"Grade":"K","EnrollmentSize":25},{"Grade":"01","EnrollmentSize":16},{"Grade":"02","EnrollmentSize":21},{"Grade":"03","EnrollmentSize":21},{"Grade":"04","EnrollmentSize":25},{"Grade":"05","EnrollmentSize":25},{"Grade":"06","EnrollmentSize":39}]},{"Year":"20032004","Teachers":13,"Students":162,"GradeEnrollment":[{"Grade":"PK","EnrollmentSize":15},{"Grade":"K","EnrollmentSize":20},{"Grade":"01","EnrollmentSize":21},{"Grade":"02","EnrollmentSize":20},{"Grade":"03","EnrollmentSize":23},{"Grade":"04","EnrollmentSize":19},{"Grade":"05","EnrollmentSize":20},{"Grade":"06","EnrollmentSize":24}]},{"Year":"20042005","Teachers":14,"Students":162,"GradeEnrollment":[{"Grade":"PK","EnrollmentSize":13},{"Grade":"K","EnrollmentSize":19},{"Grade":"01","EnrollmentSize":22},{"Grade":"02","EnrollmentSize":24},{"Grade":"03","EnrollmentSize":20},{"Grade":"04","EnrollmentSize":18},{"Grade":"05","EnrollmentSize":23},{"Grade":"06","EnrollmentSize":23}]},{"Year":"20052006","Teachers":14,"Students":155,"GradeEnrollment":[{"Grade":"PK","EnrollmentSize":17},{"Grade":"K","EnrollmentSize":21},{"Grade":"01","EnrollmentSize":20},{"Grade":"02","EnrollmentSize":24},{"Grade":"03","EnrollmentSize":25},{"Grade":"04","EnrollmentSize":12},{"Grade":"05","EnrollmentSize":15},{"Grade":"06","EnrollmentSize":21}]},{"Year":"20062007","Teachers":12,"Students":172,"GradeEnrollment":[{"Grade":"PK","EnrollmentSize":22},{"Grade":"K","EnrollmentSize":18},{"Grade":"01","EnrollmentSize":24},{"Grade":"02","EnrollmentSize":21},{"Grade":"03","EnrollmentSize":26},{"Grade":"04","EnrollmentSize":24},{"Grade":"05","EnrollmentSize":20},{"Grade":"06","EnrollmentSize":17}]},{"Year":"20072008","Teachers":0,"Students":173,"GradeEnrollment":[{"Grade":"PK","EnrollmentSize":23},{"Grade":"K","EnrollmentSize":19},{"Grade":"01","EnrollmentSize":17},{"Grade":"02","EnrollmentSize":27},{"Grade":"03","EnrollmentSize":21},{"Grade":"04","EnrollmentSize":25},{"Grade":"05","EnrollmentSize":19},{"Grade":"06","EnrollmentSize":22}]},{"Year":"20082009","Teachers":0,"Students":168,"GradeEnrollment":[{"Grade":"PK","EnrollmentSize":13},{"Grade":"K","EnrollmentSize":23},{"Grade":"01","EnrollmentSize":23},{"Grade":"02","EnrollmentSize":18},{"Grade":"03","EnrollmentSize":28},{"Grade":"04","EnrollmentSize":24},{"Grade":"05","EnrollmentSize":19},{"Grade":"06","EnrollmentSize":20}]},{"Year":"20092010","Teachers":0,"Students":188,"GradeEnrollment":[{"Grade":"PK","EnrollmentSize":21},{"Grade":"K","EnrollmentSize":24},{"Grade":"01","EnrollmentSize":24},{"Grade":"02","EnrollmentSize":23},{"Grade":"03","EnrollmentSize":21},{"Grade":"04","EnrollmentSize":28},{"Grade":"05","EnrollmentSize":25},{"Grade":"06","EnrollmentSize":22}]},{"Year":"20102011","Teachers":0,"Students":192,"GradeEnrollment":[{"Grade":"PK","EnrollmentSize":25},{"Grade":"K","EnrollmentSize":26},{"Grade":"01","EnrollmentSize":26},{"Grade":"02","EnrollmentSize":22},{"Grade":"03","EnrollmentSize":23},{"Grade":"04","EnrollmentSize":26},{"Grade":"05","EnrollmentSize":20},{"Grade":"06","EnrollmentSize":24}]},{"Year":"20112012","Teachers":0,"Students":181,"GradeEnrollment":[{"Grade":"PK","EnrollmentSize":24},{"Grade":"K","EnrollmentSize":27},{"Grade":"01","EnrollmentSize":25},{"Grade":"02","EnrollmentSize":23},{"Grade":"03","EnrollmentSize":19},{"Grade":"04","EnrollmentSize":20},{"Grade":"05","EnrollmentSize":25},{"Grade":"06","EnrollmentSize":18}]},{"Year":"20122013","Teachers":0,"Students":169,"GradeEnrollment":[{"Grade":"PK","EnrollmentSize":23},{"Grade":"K","EnrollmentSize":20},{"Grade":"01","EnrollmentSize":23},{"Grade":"02","EnrollmentSize":24},{"Grade":"03","EnrollmentSize":22},{"Grade":"04","EnrollmentSize":18},{"Grade":"05","EnrollmentSize":20},{"Grade":"06","EnrollmentSize":19}]}]}